Metadata-Version: 2.4
Name: textminer-pro-supace-how
Version: 0.2.3
Summary: 불용어 제거, 키워드 추출, 요약, 언어 감지를 제공하는 텍스트 분석 도구
Home-page: https://github.com/project/Hansupace/textminer-pro
Author: 최수한
Author-email: wagkster@naver.com
Classifier: Programming Language :: Python :: 3
Classifier: License :: OSI Approved :: MIT License
Classifier: Topic :: Text Processing :: Linguistic
Requires-Python: >=3.8
Requires-Dist: nltk>=3.8.1
Requires-Dist: scikit-learn>=1.3.0
Requires-Dist: langdetect>=1.0.9
Requires-Dist: sumy>=0.11.0
Dynamic: author
Dynamic: author-email
Dynamic: classifier
Dynamic: description
Dynamic: description-content-type
Dynamic: home-page
Dynamic: requires-dist
Dynamic: requires-python
Dynamic: summary
